sunriset/__init__.py
sunriset/calc.py
sunriset/sunriset.py
sunriset-1.0.dist-info/LICENSE
sunriset-1.0.dist-info/METADATA
sunriset-1.0.dist-info/WHEEL
sunriset-1.0.dist-info/top_level.txt
sunriset-1.0.dist-info/RECORD
