Metadata-Version: 2.1
Name: sunriset
Version: 1.0
Summary: A Solar Calculator
Home-page: https://github.com/BrianArbuckle/sunriset
Author: Brian Arbuckle
Author-email: brian@brianarbuckle.com
License: UNKNOWN
Platform: UNKNOWN
Classifier: Programming Language :: Python :: 3
Classifier: License :: OSI Approved :: MIT License
Classifier: Operating System :: OS Independent
Requires-Python: >=3.6
Requires-Dist: pytz
Requires-Dist: pandas
